odoo/addons/hr_holidays_public/README.rst
odoo/addons/hr_holidays_public/__init__.py
odoo/addons/hr_holidays_public/__manifest__.py
odoo/addons/hr_holidays_public/data/data.xml
odoo/addons/hr_holidays_public/i18n/ar.po
odoo/addons/hr_holidays_public/i18n/ca.po
odoo/addons/hr_holidays_public/i18n/ca_ES.po
odoo/addons/hr_holidays_public/i18n/de.po
odoo/addons/hr_holidays_public/i18n/es.po
odoo/addons/hr_holidays_public/i18n/fi.po
odoo/addons/hr_holidays_public/i18n/fr.po
odoo/addons/hr_holidays_public/i18n/hr.po
odoo/addons/hr_holidays_public/i18n/hr_HR.po
odoo/addons/hr_holidays_public/i18n/hr_holidays_public.pot
odoo/addons/hr_holidays_public/i18n/it.po
odoo/addons/hr_holidays_public/i18n/nl_NL.po
odoo/addons/hr_holidays_public/i18n/pl.po
odoo/addons/hr_holidays_public/i18n/pt_BR.po
odoo/addons/hr_holidays_public/i18n/ro.po
odoo/addons/hr_holidays_public/i18n/sl.po
odoo/addons/hr_holidays_public/migrations/12.0.2.0.0/post-migration.py
odoo/addons/hr_holidays_public/models/__init__.py
odoo/addons/hr_holidays_public/models/hr_holidays_public.py
odoo/addons/hr_holidays_public/models/hr_leave.py
odoo/addons/hr_holidays_public/models/hr_leave_type.py
odoo/addons/hr_holidays_public/models/resource_calendar.py
odoo/addons/hr_holidays_public/readme/CONFIGURE.rst
odoo/addons/hr_holidays_public/readme/CONTRIBUTORS.rst
odoo/addons/hr_holidays_public/readme/DESCRIPTION.rst
odoo/addons/hr_holidays_public/readme/ROADMAP.rst
odoo/addons/hr_holidays_public/readme/USAGE.rst
odoo/addons/hr_holidays_public/security/ir.model.access.csv
odoo/addons/hr_holidays_public/static/description/icon.png
odoo/addons/hr_holidays_public/static/description/icon.svg
odoo/addons/hr_holidays_public/static/description/index.html
odoo/addons/hr_holidays_public/tests/__init__.py
odoo/addons/hr_holidays_public/tests/test_holidays_calculation_common.py
odoo/addons/hr_holidays_public/tests/test_holidays_in_days_calculation.py
odoo/addons/hr_holidays_public/tests/test_holidays_in_hours_calculation.py
odoo12_addon_hr_holidays_public-12.0.1.1.3.dist-info/METADATA
odoo12_addon_hr_holidays_public-12.0.1.1.3.dist-info/WHEEL
odoo12_addon_hr_holidays_public-12.0.1.1.3.dist-info/top_level.txt
odoo12_addon_hr_holidays_public-12.0.1.1.3.dist-info/RECORD
